propileu_sdk/__init__.py
propileu_sdk/apps.py
propileu_sdk/config.py
propileu_sdk/sdk.py
propileu_sdk/entities/__init__.py
propileu_sdk/entities/base_manager.py
propileu_sdk/entities/billing.py
propileu_sdk/entities/employee.py
propileu_sdk/entities/employee_retail_store.py
propileu_sdk/entities/exceps.py
propileu_sdk/entities/industry.py
propileu_sdk/entities/office.py
propileu_sdk/entities/product.py
propileu_sdk/entities/region.py
propileu_sdk/entities/retail_store.py
tests/__init__.py
tests/integration/__init__.py
tests/integration/test_billing.py
tests/unit/__init__.py
tests/unit/test_base_manager.py
tests/unit/test_billing.py
tests/unit/test_employee.py
tests/unit/test_employee_retail_store.py
tests/unit/test_industry.py
tests/unit/test_office.py
tests/unit/test_product_family.py
tests/unit/test_region.py
tests/unit/test_retail_store.py
tests/unit/tests_product.py
propileu_sdk-1.0.0.dist-info/METADATA
propileu_sdk-1.0.0.dist-info/WHEEL
propileu_sdk-1.0.0.dist-info/top_level.txt
propileu_sdk-1.0.0.dist-info/RECORD
